Workbook

Sheet Reserves
B2: Expected Claims | C2: Expected expenses | D2: Profit | E2: Total $ Needed | F2: Reserve
A3: Year 1 | B3: ='Expected Claims'!J5 -> 9637048.3 | C3: ='Expected Expenses'!H3 -> 15661000 | D3: 30000 | E3: =SUM(B3:D3) -> 25328048 | F3: =(F4/1.05)+E3 -> 3.1460155e+08 | G3: =F3/1.05 -> 2.9962052e+08
A4: Year 2 | B4: ='Expected Claims'!J6 -> 10405485 | C4: ='Expected Expenses'!H4 -> 17886000 | D4: =D3*1.1 -> 33000 | E4: =SUM(B4:D4) -> 28324485 | F4: =(F5/1.05)+E4 -> 3.0373718e+08
A5: Year 3 | B5: ='Expected Claims'!J7 -> 11301966 | C5: ='Expected Expenses'!H5 -> 20119750 | D5: =D4*1.1 -> 36300 | E5: =SUM(B5:D5) -> 31458016 | F5: =(F6/1.05)+E5 -> 2.8918332e+08
A6: Year 4 | B6: ='Expected Claims'!J8 -> 12294502 | C6: ='Expected Expenses'!H6 -> 22362938 | D6: =D5*1.1 -> 39930 | E6: =SUM(B6:D6) -> 34697369 | F6: =(F7/1.05)+E6 -> 2.7061157e+08
A7: Year 5 | B7: ='Expected Claims'!J9 -> 13351093 | C7: ='Expected Expenses'!H7 -> 24616309 | D7: =D6*1.1 -> 43923 | E7: =SUM(B7:D7) -> 38011325 | F7: =(F8/1.05)+E7 -> 2.4770991e+08
A8: Year 6 | B8: ='Expected Claims'!J10 -> 14503750 | C8: ='Expected Expenses'!H8 -> 26880677 | D8: =D7*1.1 -> 48315.3 | E8: =SUM(B8:D8) -> 41432743 | F8: =(F9/1.05)+E8 -> 2.2018352e+08
A9: Year 7 | B9: ='Expected Claims'!J11 -> 15752474 | C9: ='Expected Expenses'!H9 -> 29156924 | D9: =D8*1.1 -> 53146.83 | E9: =SUM(B9:D9) -> 44962545 | F9: =(F10/1.05)+E9 -> 1.8768831e+08
A10: Year 8 | B10: ='Expected Claims'!J12 -> 17129275 | C10: ='Expected Expenses'!H10 -> 31446009 | D10: =D9*1.1 -> 58461.513 | E10: =SUM(B10:D10) -> 48633745 | F10: =(F11/1.05)+E10 -> 1.4986206e+08
A11: Year 9 | B11: ='Expected Claims'!J13 -> 18666153 | C11: ='Expected Expenses'!H11 -> 33748978 | D11: =D10*1.1 -> 64307.664 | E11: =SUM(B11:D11) -> 52479439 | F11: =(F12/1.05)+E11 -> 1.0628973e+08
A12: Year 10 | B12: ='Expected Claims'!J14 -> 20363100 | C12: ='Expected Expenses'!H12 -> 36066966 | D12: =D11*1.1 -> 70738.431 | E12: =SUM(B12:D12) -> 56500805 | F12: =E12 -> 56500805

Sheet Expected Claims
A2: Age | B2: Mortality_Rate | E2: Policy Holder | F2: Joe | G2: Cindy | H2: Eric | I2: Others
A3: 0 | B3: 0.00708 | E3: Face Value | F3: 10000 | G3: 1000000 | H3: 50000 | I3: 3200000000
A4: 1 | B4: 0.00176 | E4: Age | F4: 28 | G4: 43 | H4: 52 | I4: Various | J4: Total Claims for year
A5: 2 | B5: 0.00152 | E5: Year 1 | F5: =$F$3*$B31 -> 20.3 | G5: =$G$3*$B46 -> 4530 | H5: =$H$3*$B55 -> 498 | I5: =$I$3*B41 -> 9632000 | J5: =SUM(F5:I5) -> 9637048.3
A6: 3 | B6: 0.00146 | E6: Year 2 | F6: =$F$3*$B32 -> 20.8 | G6: =$G$3*$B47 -> 4920 | H6: =$H$3*$B56 -> 544.5 | I6: =$I$3*B42 -> 10400000 | J6: =SUM(F6:I6) -> 10405485
A7: 4 | B7: 0.0014 | E7: Year 3 | F7: =$F$3*$B33 -> 21.3 | G7: =$G$3*$B48 -> 5350 | H7: =$H$3*$B57 -> 595 | I7: =$I$3*B43 -> 11296000 | J7: =SUM(F7:I7) -> 11301966
A8: 5 | B8: 0.00135 | E8: Year 4 | F8: =$F$3*$B34 -> 21.9 | G8: =$G$3*$B49 -> 5830 | H8: =$H$3*$B58 -> 650 | I8: =$I$3*B44 -> 12288000 | J8: =SUM(F8:I8) -> 12294502
A9: 6 | B9: 0.0013 | E9: Year 5 | F9: =$F$3*$B35 -> 22.5 | G9: =$G$3*$B50 -> 6360 | H9: =$H$3*$B59 -> 710.5 | I9: =$I$3*B45 -> 13344000 | J9: =SUM(F9:I9) -> 13351093
A10: 7 | B10: 0.00126 | E10: Year 6 | F10: =$F$3*$B36 -> 23.2 | G10: =$G$3*$B51 -> 6950 | H10: =$H$3*$B60 -> 777 | I10: =$I$3*B46 -> 14496000 | J10: =SUM(F10:I10) -> 14503750
A11: 8 | B11: 0.00123 | E11: Year 7 | F11: =$F$3*$B37 -> 24 | G11: =$G$3*$B52 -> 7600 | H11: =$H$3*$B61 -> 850 | I11: =$I$3*B47 -> 15744000 | J11: =SUM(F11:I11) -> 15752474
A12: 9 | B12: 0.00121 | E12: Year 8 | F12: =$F$3*$B38 -> 25.1 | G12: =$G$3*$B53 -> 8320 | H12: =$H$3*$B62 -> 929.5 | I12: =$I$3*B48 -> 17120000 | J12: =SUM(F12:I12) -> 17129275
A13: 10 | B13: 0.00121 | E13: Year 9 | F13: =$F$3*$B39 -> 26.4 | G13: =$G$3*$B54 -> 9110 | H13: =$H$3*$B63 -> 1017 | I13: =$I$3*B49 -> 18656000 | J13: =SUM(F13:I13) -> 18666153
A14: 11 | B14: 0.00123 | E14: Year 10 | F14: =$F$3*$B40 -> 28 | G14: =$G$3*$B55 -> 9960 | H14: =$H$3*$B64 -> 1112 | I14: =$I$3*B50 -> 20352000 | J14: =SUM(F14:I14) -> 20363100
A15: 12 | B15: 0.00126
A16: 13 | B16: 0.00132
A17: 14 | B17: 0.00139
A18: 15 | B18: 0.00146
A19: 16 | B19: 0.00154
A20: 17 | B20: 0.00162
A21: 18 | B21: 0.00169
A22: 19 | B22: 0.00174
A23: 20 | B23: 0.00179
A24: 21 | B24: 0.00183
A25: 22 | B25: 0.00186
A26: 23 | B26: 0.00189
... A102: 99 | B102: 1

Sheet Expected Expenses
C2: Projected Sales | D2: Mortgage Payment | E2: Payroll | F2: Sales Commission | G2: Legal Fees | H2: Total Expenses
B3: Year 1 | C3: 13000000 | D3: 11000 | E3: 500000 | F3: =C3*0.05 -> 650000 | G3: 1500000 | H3: =SUM(C3:G3) -> 15661000
B4: Year 2 | C4: =C3+2000000 -> 15000000 | D4: 11000 | E4: =E3*1.1 -> 550000 | F4: =C4*0.05 -> 750000 | G4: =G3*1.05 -> 1575000 | H4: =SUM(C4:G4) -> 17886000
B5: Year 3 | C5: =C4+2000000 -> 17000000 | D5: 11000 | E5: =E4*1.1 -> 605000 | F5: =C5*0.05 -> 850000 | G5: =G4*1.05 -> 1653750 | H5: =SUM(C5:G5) -> 20119750
B6: Year 4 | C6: =C5+2000000 -> 19000000 | D6: 11000 | E6: =E5*1.1 -> 665500 | F6: =C6*0.05 -> 950000 | G6: =G5*1.05 -> 1736437.5 | H6: =SUM(C6:G6) -> 22362938
B7: Year 5 | C7: =C6+2000000 -> 21000000 | D7: 11000 | E7: =E6*1.1 -> 732050 | F7: =C7*0.05 -> 1050000 | G7: =G6*1.05 -> 1823259.4 | H7: =SUM(C7:G7) -> 24616309
B8: Year 6 | C8: =C7+2000000 -> 23000000 | D8: 11000 | E8: =E7*1.1 -> 805255 | F8: =C8*0.05 -> 1150000 | G8: =G7*1.05 -> 1914422.3 | H8: =SUM(C8:G8) -> 26880677
B9: Year 7 | C9: =C8+2000000 -> 25000000 | D9: 11000 | E9: =E8*1.1 -> 885780.5 | F9: =C9*0.05 -> 1250000 | G9: =G8*1.05 -> 2010143.5 | H9: =SUM(C9:G9) -> 29156924
B10: Year 8 | C10: =C9+2000000 -> 27000000 | D10: 11000 | E10: =E9*1.1 -> 974358.55 | F10: =C10*0.05 -> 1350000 | G10: =G9*1.05 -> 2110650.6 | H10: =SUM(C10:G10) -> 31446009
B11: Year 9 | C11: =C10+2000000 -> 29000000 | D11: 11000 | E11: =E10*1.1 -> 1071794.4 | F11: =C11*0.05 -> 1450000 | G11: =G10*1.05 -> 2216183.2 | H11: =SUM(C11:G11) -> 33748978
B12: Year 10 | C12: =C11+2000000 -> 31000000 | D12: 11000 | E12: =E11*1.1 -> 1178973.8 | F12: =C12*0.05 -> 1550000 | G12: =G11*1.05 -> 2326992.3 | H12: =SUM(C12:G12) -> 36066966
